easyml/__init__.py
easyml/cache.py
easyml/cli.py
easyml/config.py
easyml/ensemble.py
easyml/evaluation.py
easyml/models.py
easyml/monitoring.py
easyml/preprocessing.py
easyml/utils.py
easyml/visualization.py
easyml_framework-1.3.2.dist-info/licenses/LICENSE
easyml_framework-1.3.2.dist-info/METADATA
easyml_framework-1.3.2.dist-info/WHEEL
easyml_framework-1.3.2.dist-info/entry_points.txt
easyml_framework-1.3.2.dist-info/top_level.txt
easyml_framework-1.3.2.dist-info/RECORD
