Metadata-Version: 2.4
Name: easyml-framework
Version: 1.3.2
Summary: Framework ML ultra-simple avec cache intelligent, ensemble learning et monitoring automatique
Home-page: https://github.com/jeremy-dev/easyml-framework
Author: Jeremy Dev
Author-email: jeremy.dev@example.com
Project-URL: Bug Reports, https://github.com/jeremy-dev/easyml-framework/issues
Project-URL: Source, https://github.com/jeremy-dev/easyml-framework
Project-URL: Documentation, https://github.com/jeremy-dev/easyml-framework/blob/main/README.md
Classifier: Development Status :: 5 - Production/Stable
Classifier: Intended Audience :: Developers
Classifier: Intended Audience :: Science/Research
Classifier: License :: OSI Approved :: MIT License
Classifier: Operating System :: OS Independent
Classifier: Programming Language :: Python :: 3
Classifier: Programming Language :: Python :: 3.7
Classifier: Programming Language :: Python :: 3.8
Classifier: Programming Language :: Python :: 3.9
Classifier: Programming Language :: Python :: 3.10
Classifier: Programming Language :: Python :: 3.11
Classifier: Topic :: Scientific/Engineering :: Artificial Intelligence
Classifier: Topic :: Software Development :: Libraries :: Python Modules
Requires-Python: >=3.7
License-File: LICENSE
Requires-Dist: numpy>=1.19.0
Requires-Dist: pandas>=1.2.0
Requires-Dist: scikit-learn>=1.0.0
Requires-Dist: matplotlib>=3.3.0
Requires-Dist: seaborn>=0.11.0
Requires-Dist: joblib>=1.0.0
Requires-Dist: tqdm>=4.60.0
Requires-Dist: pyyaml>=5.4.0
Requires-Dist: requests>=2.25.0
Provides-Extra: deep
Requires-Dist: tensorflow>=2.8.0; extra == "deep"
Requires-Dist: torch>=1.10.0; extra == "deep"
Provides-Extra: nlp
Requires-Dist: nltk>=3.6; extra == "nlp"
Requires-Dist: spacy>=3.2.0; extra == "nlp"
Provides-Extra: viz
Requires-Dist: plotly>=5.0.0; extra == "viz"
Requires-Dist: bokeh>=2.3.0; extra == "viz"
Provides-Extra: dev
Requires-Dist: pytest>=6.0; extra == "dev"
Requires-Dist: black>=21.0; extra == "dev"
Requires-Dist: flake8>=3.8; extra == "dev"
Dynamic: author
Dynamic: author-email
Dynamic: classifier
Dynamic: description
Dynamic: description-content-type
Dynamic: home-page
Dynamic: license-file
Dynamic: project-url
Dynamic: provides-extra
Dynamic: requires-dist
Dynamic: requires-python
Dynamic: summary
